{
  "all_routes_executed": true,
  "candidate_package_path": "D:\\vggt\\vggt-main\\output\\surface_research_preflight_local\\V50_final_promotion_transaction\\candidate_package_v50",
  "created_utc": "2026-05-08T21:48:04Z",
  "decision": "V50 strict promotion passed and wrote formal candidate package/registry.",
  "forbidden_hit_count": 0,
  "formal_cloud_unblocked": true,
  "mentor_decision_needed": false,
  "prior_stage_statuses": {
    "v29": "DONE_PASS",
    "v30": "DONE_PASS",
    "v31": "DONE_PASS",
    "v32": "DONE_PASS",
    "v33": "DONE_PASS",
    "v34": "DONE_PASS",
    "v35": "DONE_PASS",
    "v36": "MISSING"
  },
  "registry_entry_path": "D:\\vggt\\vggt-main\\output\\surface_research_preflight_local\\V50_final_promotion_transaction\\strict_registry_entry_v50.json",
  "remaining_blockers": [],
  "stage_statuses": {
    "v44": "DONE_PASS",
    "v45": "DONE_PASS",
    "v46": "DONE_PASS",
    "v47": "DONE_PASS",
    "v48": "DONE_PASS",
    "v49": "DONE_PASS"
  },
  "status": "DONE_PASS",
  "strict_candidate_passes": 1,
  "strict_teacher_passes": 0,
  "task": "v50_final_promotion_transaction",
  "teacher_package_path": null,
  "writes_package": true,
  "writes_strict_pass": true,
  "writes_strict_registry": true
}
