{
  "identity_l2": 0.0,
  "loss_start": 1.5999997060589521e-07,
  "loss_end": 3.881581278619706e-08,
  "grad_nonzero": true,
  "changed_pixels": 12,
  "outside_changed_pixels": 0,
  "target_indices": 12,
  "trace": [
    {
      "step": 0,
      "loss": 1.5999997060589521e-07,
      "grad_norm": 7.670298529660613e-08
    },
    {
      "step": 1,
      "loss": 1.5473003145416442e-07,
      "grad_norm": 8.973415444035737e-08
    },
    {
      "step": 2,
      "loss": 1.4933500835923041e-07,
      "grad_norm": 1.0473536904420655e-07
    },
    {
      "step": 3,
      "loss": 1.4349200228025438e-07,
      "grad_norm": 1.2221105283316547e-07
    },
    {
      "step": 4,
      "loss": 1.3690731748283724e-07,
      "grad_norm": 1.428099272171579e-07
    },
    {
      "step": 5,
      "loss": 1.2925916337280796e-07,
      "grad_norm": 1.6729711793672664e-07
    },
    {
      "step": 6,
      "loss": 1.2016018047233956e-07,
      "grad_norm": 1.9647546167789187e-07
    },
    {
      "step": 7,
      "loss": 1.0913313985838613e-07,
      "grad_norm": 2.3090083089982727e-07
    },
    {
      "step": 8,
      "loss": 9.562049285705143e-08,
      "grad_norm": 2.700106547237624e-07
    },
    {
      "step": 9,
      "loss": 7.910446697678708e-08,
      "grad_norm": 3.095946263798055e-07
    },
    {
      "step": 10,
      "loss": 5.9561759968573824e-08,
      "grad_norm": 3.348798989222246e-07
    },
    {
      "step": 11,
      "loss": 3.881581278619706e-08,
      "grad_norm": 3.065707216975966e-07
    }
  ],
  "pass": true
}
